pydot/__init__.py
pydot/core.py
pydot/dot_parser.py
pydot/exceptions.py
pydot/_vendor/__init__.py
pydot/_vendor/tempfile.py
pydot-3.0.2.dist-info/METADATA
pydot-3.0.2.dist-info/MIT.txt
pydot-3.0.2.dist-info/Python-2.0.txt
pydot-3.0.2.dist-info/WHEEL
pydot-3.0.2.dist-info/top_level.txt
pydot-3.0.2.dist-info/RECORD
